{
  "success": true,
  "lastUpdated": 1764111619052,
  "totalServers": 44238,
  "totalPlayers": 184201,
  "resources": {
    "mnr_cayo": {
      "serverRank": 1138,
      "playerRank": 1788,
      "serverRankChange": 15,
      "playerRankChange": 69,
      "servers": 695,
      "players": 3426
    },
    "mnr_postals": {
      "serverRank": 5724,
      "playerRank": 12859,
      "serverRankChange": -288,
      "playerRankChange": 1469,
      "servers": 167,
      "players": 564
    },
    "mnr_sitanywhere": {
      "serverRank": 12012,
      "playerRank": 14528,
      "serverRankChange": 0,
      "playerRankChange": 0,
      "servers": 82,
      "players": 495
    },
    "mnr_fuel": {
      "serverRank": 24199,
      "playerRank": 35680,
      "serverRankChange": 0,
      "playerRankChange": 0,
      "servers": 39,
      "players": 245
    },
    "mnr_elevators": {
      "serverRank": 22406,
      "playerRank": 139615,
      "serverRankChange": 0,
      "playerRankChange": 0,
      "servers": 43,
      "players": 37
    },
    "mnr_blips": {
      "serverRank": 49355,
      "playerRank": 141720,
      "serverRankChange": 0,
      "playerRankChange": 0,
      "servers": 17,
      "players": 36
    },
    "mnr_showid": {
      "serverRank": 96905,
      "playerRank": 323833,
      "serverRankChange": 0,
      "playerRankChange": 0,
      "servers": 7,
      "players": 3
    },
    "mnr_ipl": {
      "serverRank": 78826,
      "playerRank": 226468,
      "serverRankChange": 0,
      "playerRankChange": 0,
      "servers": 9,
      "players": 11
    },
    "mnr_anticl": {
      "serverRank": 118427,
      "playerRank": 209809,
      "serverRankChange": 0,
      "playerRankChange": 0,
      "servers": 5,
      "players": 14
    },
    "mnr_zones": {
      "serverRank": 109911,
      "playerRank": 403029,
      "serverRankChange": 0,
      "playerRankChange": 0,
      "servers": 6,
      "players": 1
    },
    "mnr_consumables": {
      "serverRank": 153144,
      "playerRank": 560554,
      "serverRankChange": 0,
      "playerRankChange": 0,
      "servers": 4,
      "players": 0
    },
    "mnr_dispatch": {
      "serverRank": 308585,
      "playerRank": 367250,
      "serverRankChange": 0,
      "playerRankChange": 0,
      "servers": 2,
      "players": 2
    },
    "mnr_loadingscreen": {
      "serverRank": 299594,
      "playerRank": 332563,
      "serverRankChange": 0,
      "playerRankChange": 0,
      "servers": 2,
      "players": 3
    }
  }
}