{
  "success": true,
  "lastUpdated": 1765040455760,
  "totalServers": 44933,
  "totalPlayers": 197024,
  "resources": {
    "mnr_cayo": {
      "serverRank": 1082,
      "playerRank": 1701,
      "serverRankChange": 17,
      "playerRankChange": -202,
      "servers": 740,
      "players": 3547
    },
    "mnr_postals": {
      "serverRank": 5407,
      "playerRank": 20224,
      "serverRankChange": -73,
      "playerRankChange": -8873,
      "servers": 178,
      "players": 497
    },
    "mnr_sitanywhere": {
      "serverRank": 14064,
      "playerRank": 28517,
      "serverRankChange": -254,
      "playerRankChange": -11732,
      "servers": 72,
      "players": 351
    },
    "mnr_fuel": {
      "serverRank": 29697,
      "playerRank": 43323,
      "serverRankChange": 228,
      "playerRankChange": -9595,
      "servers": 32,
      "players": 224
    },
    "mnr_elevators": {
      "serverRank": 28157,
      "playerRank": 51158,
      "serverRankChange": -1550,
      "playerRankChange": 51367,
      "servers": 34,
      "players": 182
    },
    "mnr_blips": {
      "serverRank": 46208,
      "playerRank": 147925,
      "serverRankChange": 213,
      "playerRankChange": -41568,
      "servers": 19,
      "players": 34
    },
    "mnr_showid": {
      "serverRank": 109854,
      "playerRank": 331809,
      "serverRankChange": 3352,
      "playerRankChange": 100142,
      "servers": 6,
      "players": 3
    },
    "mnr_ipl": {
      "serverRank": 95604,
      "playerRank": 192577,
      "serverRankChange": 465,
      "playerRankChange": -12354,
      "servers": 7,
      "players": 18
    },
    "mnr_anticl": {
      "serverRank": 124869,
      "playerRank": 332810,
      "serverRankChange": -1598,
      "playerRankChange": -66243,
      "servers": 5,
      "players": 3
    },
    "mnr_zones": {
      "serverRank": 121398,
      "playerRank": 237801,
      "serverRankChange": 8395,
      "playerRankChange": 196231,
      "servers": 5,
      "players": 10
    },
    "mnr_consumables": {
      "serverRank": 157494,
      "playerRank": 585066,
      "serverRankChange": -3221,
      "playerRankChange": -147545,
      "servers": 4,
      "players": 0
    },
    "mnr_dispatch": {
      "serverRank": 945212,
      "playerRank": 945212,
      "serverRankChange": 6061,
      "playerRankChange": 6061,
      "servers": 1,
      "players": 0
    },
    "mnr_loadingscreen": {
      "serverRank": 288051,
      "playerRank": 269330,
      "serverRankChange": -24956,
      "playerRankChange": -100676,
      "servers": 2,
      "players": 7
    }
  }
}