{
  "success": true,
  "lastUpdated": 1764158422062,
  "totalServers": 44123,
  "totalPlayers": 85019,
  "resources": {
    "mnr_cayo": {
      "serverRank": 1131,
      "playerRank": 1310,
      "serverRankChange": 7,
      "playerRankChange": 478,
      "servers": 691,
      "players": 1932
    },
    "mnr_postals": {
      "serverRank": 5651,
      "playerRank": 15281,
      "serverRankChange": 73,
      "playerRankChange": -2422,
      "servers": 166,
      "players": 292
    },
    "mnr_sitanywhere": {
      "serverRank": 12014,
      "playerRank": 40803,
      "serverRankChange": -2,
      "playerRankChange": -26275,
      "servers": 81,
      "players": 98
    },
    "mnr_fuel": {
      "serverRank": 23936,
      "playerRank": 63441,
      "serverRankChange": 263,
      "playerRankChange": -27761,
      "servers": 39,
      "players": 55
    },
    "mnr_elevators": {
      "serverRank": 22288,
      "playerRank": 32525,
      "serverRankChange": 118,
      "playerRankChange": 107090,
      "servers": 42,
      "players": 126
    },
    "mnr_blips": {
      "serverRank": 49430,
      "playerRank": 209931,
      "serverRankChange": -75,
      "playerRankChange": -68211,
      "servers": 17,
      "players": 4
    },
    "mnr_showid": {
      "serverRank": 94214,
      "playerRank": 232557,
      "serverRankChange": 2691,
      "playerRankChange": 91276,
      "servers": 7,
      "players": 3
    },
    "mnr_ipl": {
      "serverRank": 87450,
      "playerRank": 307367,
      "serverRankChange": -8624,
      "playerRankChange": -80899,
      "servers": 8,
      "players": 1
    },
    "mnr_anticl": {
      "serverRank": 126263,
      "playerRank": 469323,
      "serverRankChange": -7836,
      "playerRankChange": -259514,
      "servers": 5,
      "players": 0
    },
    "mnr_zones": {
      "serverRank": 104520,
      "playerRank": 233453,
      "serverRankChange": 5391,
      "playerRankChange": 169576,
      "servers": 6,
      "players": 3
    },
    "mnr_consumables": {
      "serverRank": 151131,
      "playerRank": 475951,
      "serverRankChange": 2013,
      "playerRankChange": 84603,
      "servers": 4,
      "players": 0
    },
    "mnr_dispatch": {
      "serverRank": 365388,
      "playerRank": 546712,
      "serverRankChange": -56803,
      "playerRankChange": -179462,
      "servers": 2,
      "players": 0
    },
    "mnr_loadingscreen": {
      "serverRank": 365389,
      "playerRank": 546713,
      "serverRankChange": -65795,
      "playerRankChange": -214150,
      "servers": 2,
      "players": 0
    }
  }
}