{
  "success": true,
  "lastUpdated": 1764723642772,
  "totalServers": 44293,
  "totalPlayers": 161727,
  "resources": {
    "mnr_cayo": {
      "serverRank": 1077,
      "playerRank": 1763,
      "serverRankChange": -3,
      "playerRankChange": -82,
      "servers": 746,
      "players": 3141
    },
    "mnr_postals": {
      "serverRank": 5381,
      "playerRank": 11045,
      "serverRankChange": -72,
      "playerRankChange": 283,
      "servers": 179,
      "players": 653
    },
    "mnr_sitanywhere": {
      "serverRank": 12502,
      "playerRank": 22592,
      "serverRankChange": 14,
      "playerRankChange": -7781,
      "servers": 81,
      "players": 317
    },
    "mnr_fuel": {
      "serverRank": 28266,
      "playerRank": 74420,
      "serverRankChange": -68,
      "playerRankChange": -39794,
      "servers": 34,
      "players": 87
    },
    "mnr_elevators": {
      "serverRank": 25819,
      "playerRank": 129970,
      "serverRankChange": 39,
      "playerRankChange": 1001,
      "servers": 38,
      "players": 35
    },
    "mnr_blips": {
      "serverRank": 44480,
      "playerRank": 136176,
      "serverRankChange": -7,
      "playerRankChange": -20620,
      "servers": 20,
      "players": 32
    },
    "mnr_showid": {
      "serverRank": 99027,
      "playerRank": 336458,
      "serverRankChange": 2242,
      "playerRankChange": 227392,
      "servers": 7,
      "players": 2
    },
    "mnr_ipl": {
      "serverRank": 97643,
      "playerRank": 284435,
      "serverRankChange": 400,
      "playerRankChange": 21971,
      "servers": 7,
      "players": 4
    },
    "mnr_anticl": {
      "serverRank": 123766,
      "playerRank": 285592,
      "serverRankChange": -142,
      "playerRankChange": 4771,
      "servers": 5,
      "players": 4
    },
    "mnr_zones": {
      "serverRank": 113639,
      "playerRank": 542036,
      "serverRankChange": -2501,
      "playerRankChange": -182948,
      "servers": 6,
      "players": 0
    },
    "mnr_consumables": {
      "serverRank": 157667,
      "playerRank": 549393,
      "serverRankChange": -4700,
      "playerRankChange": -133333,
      "servers": 4,
      "players": 0
    },
    "mnr_dispatch": {
      "serverRank": 933889,
      "playerRank": 933889,
      "serverRankChange": 8673,
      "playerRankChange": 8673,
      "servers": 1,
      "players": 0
    },
    "mnr_loadingscreen": {
      "serverRank": 382768,
      "playerRank": 610698,
      "serverRankChange": -112285,
      "playerRankChange": -413377,
      "servers": 2,
      "players": 0
    }
  }
}