{
  "success": true,
  "lastUpdated": 1764914432085,
  "totalServers": 44216,
  "totalPlayers": 102882,
  "resources": {
    "mnr_cayo": {
      "serverRank": 1085,
      "playerRank": 1279,
      "serverRankChange": 0,
      "playerRankChange": 299,
      "servers": 740,
      "players": 2936
    },
    "mnr_postals": {
      "serverRank": 5386,
      "playerRank": 10420,
      "serverRankChange": -73,
      "playerRankChange": 1367,
      "servers": 179,
      "players": 493
    },
    "mnr_sitanywhere": {
      "serverRank": 13010,
      "playerRank": 33650,
      "serverRankChange": -107,
      "playerRankChange": -17915,
      "servers": 78,
      "players": 178
    },
    "mnr_fuel": {
      "serverRank": 28388,
      "playerRank": 90181,
      "serverRankChange": -63,
      "playerRankChange": -56063,
      "servers": 34,
      "players": 43
    },
    "mnr_elevators": {
      "serverRank": 26972,
      "playerRank": 80150,
      "serverRankChange": 241,
      "playerRankChange": 23662,
      "servers": 36,
      "players": 53
    },
    "mnr_blips": {
      "serverRank": 46394,
      "playerRank": 142371,
      "serverRankChange": -251,
      "playerRankChange": -46315,
      "servers": 19,
      "players": 16
    },
    "mnr_showid": {
      "serverRank": 113171,
      "playerRank": 476163,
      "serverRankChange": -13848,
      "playerRankChange": -116540,
      "servers": 6,
      "players": 0
    },
    "mnr_ipl": {
      "serverRank": 88862,
      "playerRank": 278859,
      "serverRankChange": -1979,
      "playerRankChange": -95981,
      "servers": 8,
      "players": 2
    },
    "mnr_anticl": {
      "serverRank": 126735,
      "playerRank": 331187,
      "serverRankChange": 2507,
      "playerRankChange": 85751,
      "servers": 5,
      "players": 1
    },
    "mnr_zones": {
      "serverRank": 124338,
      "playerRank": 282056,
      "serverRankChange": -13160,
      "playerRankChange": 78599,
      "servers": 5,
      "players": 2
    },
    "mnr_consumables": {
      "serverRank": 156695,
      "playerRank": 486866,
      "serverRankChange": 1540,
      "playerRankChange": 91142,
      "servers": 4,
      "players": 0
    },
    "mnr_dispatch": {
      "serverRank": 916454,
      "playerRank": 916454,
      "serverRankChange": 27284,
      "playerRankChange": 27284,
      "servers": 1,
      "players": 0
    },
    "mnr_loadingscreen": {
      "serverRank": 374862,
      "playerRank": 563610,
      "serverRankChange": -119369,
      "playerRankChange": -419731,
      "servers": 2,
      "players": 0
    }
  }
}